__init__.py
taalcr/__init__.py
taalcr/cli.py
taalcr/main.py
taalcr/run_wrappers.py
taalcr/convo_turns/__init__.py
taalcr/convo_turns/digital_convo_turns_analysis.py
taalcr/powers/__init__.py
taalcr/powers/automation_validation.py
taalcr/powers/powers_coding_analysis.py
taalcr/powers/powers_coding_files.py
taalcr/utils/__init__.py
taalcr/utils/auxiliary.py
taalcr-0.2.0.dist-info/licenses/LICENSE.txt
taalcr-0.2.0.dist-info/METADATA
taalcr-0.2.0.dist-info/WHEEL
taalcr-0.2.0.dist-info/entry_points.txt
taalcr-0.2.0.dist-info/top_level.txt
taalcr-0.2.0.dist-info/RECORD
