Metadata-Version: 2.4
Name: taalcr
Version: 0.2.0
Summary: Toolkit for Aggregate Analysis of Language in Conversation, for Research
Author: Nick McCloskey
License: MIT
Classifier: Programming Language :: Python :: 3
Classifier: License :: OSI Approved :: MIT License
Classifier: Operating System :: OS Independent
Requires-Python: >=3.12
License-File: LICENSE.txt
Requires-Dist: numpy==1.26.4
Requires-Dist: pandas>=2.0.3
Requires-Dist: pingouin==0.5.5
Requires-Dist: scikit_learn>=1.7.2
Requires-Dist: scipy>=1.16.2
Requires-Dist: spacy==3.8.7
Requires-Dist: streamlit>=1.45.1
Requires-Dist: tqdm>=4.67.1
Requires-Dist: rascal_speech==0.2.0
Requires-Dist: spacy[transformers]>=3.8
Provides-Extra: dev
Requires-Dist: pytest; extra == "dev"
Dynamic: license-file
